{
 "SoundBanksInfo": {
  "Platform": "Mac",
  "BasePlatform": "Mac",
  "SchemaVersion": "16",
  "SoundBankVersion": "150",
  "SoundBanks": [
   {
    "Id": "4281112222",
    "Type": "Event",
    "GUID": "{1261A477-2724-43B9-97F1-1271FEAF1150}",
    "Language": "SFX",
    "Hash": "{12CCB978-5301-AC5E-2862-DA8AE967A443}",
    "ObjectPath": "Play_Env_Trowel_SeedPlant",
    "ShortName": "Play_Env_Trowel_SeedPlant",
    "Path": "Event/Play_Env_Trowel_SeedPlant.bnk",
    "Media": [
     {
      "Id": "438329037",
      "Language": "SFX",
      "Streaming": "false",
      "Location": "Loose",
      "ShortName": "Env_Trowel-SeedPlant-002.wav",
      "Path": "Media/438329037.wem",
      "CachePath": "SFX/Env_Trowel-SeedPlant-002_F06BAF76.wem"
     },
     {
      "Id": "1014697496",
      "Language": "SFX",
      "Streaming": "false",
      "Location": "Loose",
      "ShortName": "Env_Trowel-SeedPlant-003.wav",
      "Path": "Media/1014697496.wem",
      "CachePath": "SFX/Env_Trowel-SeedPlant-003_F06BAF76.wem"
     },
     {
      "Id": "1023870359",
      "Language": "SFX",
      "Streaming": "false",
      "Location": "Loose",
      "ShortName": "Env_Trowel-SeedPlant-001.wav",
      "Path": "Media/1023870359.wem",
      "CachePath": "SFX/Env_Trowel-SeedPlant-001_F06BAF76.wem"
     }
    ],
    "Events": [
     {
      "Id": "4281112222",
      "Name": "Play_Env_Trowel_SeedPlant",
      "ObjectPath": "\\Events\\WU_Main\\Environment\\Tools\\Play_Env_Trowel_SeedPlant",
      "GUID": "{1261A477-2724-43B9-97F1-1271FEAF1150}",
      "DurationType": "OneShot",
      "DurationMin": "1.7817974",
      "DurationMax": "2.244924",
      "MediaRefs": [
       {
        "Id": "438329037"
       },
       {
        "Id": "1014697496"
       },
       {
        "Id": "1023870359"
       }
      ]
     }
    ]
   }
  ],
  "FileHash": "{9FEDF948-6581-5D6C-4342-9A711D176C16}"
 }
}