<?xml version="1.0" encoding="utf-8"?>
<SoundBanksInfo Platform="Windows" BasePlatform="Windows" SchemaVersion="16" SoundBankVersion="150">
	<SoundBanks>
		<SoundBank Id="3509013868" Type="Event" GUID="{C0F06098-CAAB-41C6-A972-07E1B3D77B33}" Language="SFX" Hash="{20452142-9236-8016-E5C9-A42314074547}">
			<ObjectPath>Play_Env_Trowel_PickUp</ObjectPath>
			<ShortName>Play_Env_Trowel_PickUp</ShortName>
			<Path>Event/Play_Env_Trowel_PickUp.bnk</Path>
			<Media>
				<File Id="61903052" Language="SFX" Streaming="false" Location="Loose">
					<ShortName>Mus_Tone_C5.wav</ShortName>
					<Path>Media/61903052.wem</Path>
					<CachePath>SFX/Mus_Tone_C5_F06BAF76.wem</CachePath>
				</File>
				<File Id="82609520" Language="SFX" Streaming="false" Location="Loose">
					<ShortName>Mus_Tone_C4.wav</ShortName>
					<Path>Media/82609520.wem</Path>
					<CachePath>SFX/Mus_Tone_C4_F06BAF76.wem</CachePath>
				</File>
				<File Id="191846235" Language="SFX" Streaming="false" Location="Loose">
					<ShortName>Mus_Tone_E4.wav</ShortName>
					<Path>Media/191846235.wem</Path>
					<CachePath>SFX/Mus_Tone_E4_F06BAF76.wem</CachePath>
				</File>
				<File Id="292968602" Language="SFX" Streaming="false" Location="Loose">
					<ShortName>Env_Trowel-PickUp-001.wav</ShortName>
					<Path>Media/292968602.wem</Path>
					<CachePath>SFX/Env_Trowel-PickUp-001_F06BAF76.wem</CachePath>
				</File>
				<File Id="332250347" Language="SFX" Streaming="false" Location="Loose">
					<ShortName>Env_Trowel-PickUp-003.wav</ShortName>
					<Path>Media/332250347.wem</Path>
					<CachePath>SFX/Env_Trowel-PickUp-003_F06BAF76.wem</CachePath>
				</File>
				<File Id="515549105" Language="SFX" Streaming="false" Location="Loose">
					<ShortName>Env_Trowel-PickUp-002.wav</ShortName>
					<Path>Media/515549105.wem</Path>
					<CachePath>SFX/Env_Trowel-PickUp-002_F06BAF76.wem</CachePath>
				</File>
				<File Id="535351334" Language="SFX" Streaming="false" Location="Loose">
					<ShortName>Mus_Tone_G4.wav</ShortName>
					<Path>Media/535351334.wem</Path>
					<CachePath>SFX/Mus_Tone_G4_F06BAF76.wem</CachePath>
				</File>
				<File Id="769164870" Language="SFX" Streaming="false" Location="Loose">
					<ShortName>Mus_Tone_B4.wav</ShortName>
					<Path>Media/769164870.wem</Path>
					<CachePath>SFX/Mus_Tone_B4_F06BAF76.wem</CachePath>
				</File>
			</Media>
			<Events>
				<Event Id="3509013868" Name="Play_Env_Trowel_PickUp" ObjectPath="\Events\WU_Main\Environment\Garden\Play_Env_Trowel_PickUp" GUID="{C0F06098-CAAB-41C6-A972-07E1B3D77B33}" DurationType="OneShot" DurationMin="4" DurationMax="4">
					<MediaRefs>
						<MediaRef Id="61903052"/>
						<MediaRef Id="82609520"/>
						<MediaRef Id="191846235"/>
						<MediaRef Id="292968602"/>
						<MediaRef Id="332250347"/>
						<MediaRef Id="515549105"/>
						<MediaRef Id="535351334"/>
						<MediaRef Id="769164870"/>
					</MediaRefs>
				</Event>
			</Events>
		</SoundBank>
	</SoundBanks>
	<FileHash>{0F150130-9E1B-8D2C-1387-A074A3A58B87}</FileHash>
</SoundBanksInfo>
