{
 "SoundBanksInfo": {
  "Platform": "Windows",
  "BasePlatform": "Windows",
  "SchemaVersion": "16",
  "SoundBankVersion": "150",
  "SoundBanks": [
   {
    "Id": "2940245297",
    "Type": "Event",
    "GUID": "{439F0EFE-EF68-487D-A78C-A4CAFF3188FC}",
    "Language": "SFX",
    "Hash": "{C7941134-A45E-A8FC-CDE2-403ED72347D3}",
    "ObjectPath": "Play_Env_ShopBell",
    "ShortName": "Play_Env_ShopBell",
    "Path": "Event/Play_Env_ShopBell.bnk",
    "Media": [
     {
      "Id": "398633420",
      "Language": "SFX",
      "Streaming": "false",
      "Location": "Loose",
      "ShortName": "Env_ShopBell.wav",
      "Path": "Media/398633420.wem",
      "CachePath": "SFX/Env_ShopBell_F06BAF76.wem"
     }
    ],
    "Events": [
     {
      "Id": "2940245297",
      "Name": "Play_Env_ShopBell",
      "ObjectPath": "\\Events\\WU_Main\\Environment\\Play_Env_ShopBell",
      "GUID": "{439F0EFE-EF68-487D-A78C-A4CAFF3188FC}",
      "DurationType": "OneShot",
      "DurationMin": "1.125",
      "DurationMax": "1.125",
      "MediaRefs": [
       {
        "Id": "398633420"
       }
      ]
     }
    ]
   }
  ],
  "FileHash": "{2BC872DC-05E1-C36B-E916-4A92C1ACAEDD}"
 }
}